algo_playground/__init__.py
algo_playground/cli.py
algo_playground/algorithms/__init__.py
algo_playground/algorithms/graphs.py
algo_playground/algorithms/searching.py
algo_playground/algorithms/sorting.py
algo_playground/visual/__init__.py
algo_playground/visual/animator.py
algo_playground-0.1.2.dist-info/METADATA
algo_playground-0.1.2.dist-info/WHEEL
algo_playground-0.1.2.dist-info/entry_points.txt
algo_playground-0.1.2.dist-info/licenses/LICENSE
algo_playground-0.1.2.dist-info/RECORD
