Metadata-Version: 2.4
Name: algo-playground
Version: 0.1.2
Summary: Interactive terminal playground for classic algorithms (sorting, searching, graphs)
Project-URL: Homepage, https://github.com/ibrahemassa/algo_playground
Project-URL: Repository, https://github.com/ibrahemassa/algo_playground
Author: Ibrahemassa
License: MIT License
License-File: LICENSE
Keywords: algorithms,cli,education,graphs,searching,sorting
Classifier: Environment :: Console
Classifier: License :: OSI Approved :: MIT License
Classifier: Operating System :: OS Independent
Classifier: Programming Language :: Python :: 3
Classifier: Programming Language :: Python :: 3 :: Only
Classifier: Programming Language :: Python :: 3.9
Classifier: Programming Language :: Python :: 3.10
Classifier: Programming Language :: Python :: 3.11
Classifier: Programming Language :: Python :: 3.12
Classifier: Topic :: Education
Classifier: Topic :: Software Development :: Libraries
Requires-Python: >=3.9
Requires-Dist: click>=8.0
Requires-Dist: rich>=13.0
